setup.py
json_object.egg-info/PKG-INFO
json_object.egg-info/SOURCES.txt
json_object.egg-info/dependency_links.txt
json_object.egg-info/not-zip-safe
json_object.egg-info/top_level.txt
jsonobject/JsonObject.py
jsonobject/__init__.py