Metadata-Version: 1.1
Name: json-object
Version: 0.0.1
Summary: F(x) Json Object Package
Home-page: https://github.com/fdexfinancing/json-object
Author: F(x)
Author-email: ti@fdex.com.br
License: MIT
Download-URL: https://github.com/fdexfinancing/json-object/tarball/0.0.1
Platform: any
